k5test/__init__.py
k5test/_utils.py
k5test/realm.py
k5test/unit.py
k5test-0.10.4.dist-info/K5TEST-LICENSE.txt
k5test-0.10.4.dist-info/LICENSE.txt
k5test-0.10.4.dist-info/METADATA
k5test-0.10.4.dist-info/WHEEL
k5test-0.10.4.dist-info/top_level.txt
k5test-0.10.4.dist-info/RECORD
