Metadata-Version: 2.1
Name: k5test
Version: 0.10.4
Summary: A library for testing Python applications in self-contained Kerberos 5 environments
Home-page: https://github.com/pythongssapi/k5test
Author: The Python GSSAPI Team
Author-email: sross@redhat.com
Keywords: gssapi,security
Classifier: Development Status :: 4 - Beta
Classifier: Programming Language :: Python
Classifier: Programming Language :: Python :: 3
Classifier: Programming Language :: Python :: 3.6
Classifier: Programming Language :: Python :: 3.7
Classifier: Programming Language :: Python :: 3.8
Classifier: Programming Language :: Python :: 3.9
Classifier: Programming Language :: Python :: 3.10
Classifier: Programming Language :: Python :: 3.11
Classifier: Intended Audience :: Developers
Classifier: License :: OSI Approved :: ISC License (ISCL)
Classifier: License :: OSI Approved :: MIT License
Classifier: Programming Language :: Python :: Implementation :: CPython
Classifier: Topic :: Security
Requires-Python: >=3.6
License-File: LICENSE.txt
License-File: K5TEST-LICENSE.txt
Provides-Extra: extension_test
Requires-Dist: gssapi ; extra == 'extension_test'
